README.md
setup.py
jira_ticket_migrate/__init__.py
jira_ticket_migrate/jira.py
jira_ticket_migrate/main.py
jira_ticket_migrate/runtime_args.py
jira_ticket_migrate/version.py
jira_ticket_migrate.egg-info/PKG-INFO
jira_ticket_migrate.egg-info/SOURCES.txt
jira_ticket_migrate.egg-info/dependency_links.txt
jira_ticket_migrate.egg-info/entry_points.txt
jira_ticket_migrate.egg-info/requires.txt
jira_ticket_migrate.egg-info/top_level.txt