Metadata-Version: 2.1
Name: jira-ticket-migrate
Version: 0.1.3
Summary: Migrate tickets from one Jira to another Jira
Home-page: https://github.com/mwiens91/jira-ticket-migrate
Author: Matt Wiens
Author-email: mwiens91@gmail.com
License: MIT
Platform: UNKNOWN
Classifier: Development Status :: 4 - Beta
Classifier: License :: OSI Approved :: MIT License
Classifier: Natural Language :: English
Classifier: Programming Language :: Python
Classifier: Programming Language :: Python :: 3
Classifier: Programming Language :: Python :: 3.6
Classifier: Programming Language :: Python :: 3.7
Requires-Python: >=3.6.0
